opensearch_redirect_esa/__init__.py
opensearch_redirect_esa/asgi.py
opensearch_redirect_esa/settings.py
opensearch_redirect_esa/templates/base.html
opensearch_redirect_esa/templates/base0.html
opensearch_redirect_esa/urls.py
opensearch_redirect_esa/views.py
opensearch_redirect_esa/wsgi.py
opensearch_redirect_esa-0.0.1.dist-info/METADATA
opensearch_redirect_esa-0.0.1.dist-info/WHEEL
opensearch_redirect_esa-0.0.1.dist-info/RECORD
