Metadata-Version: 2.1
Name: opensearch-redirect-esa
Version: 0.0.1
Summary: Init
Author: dwest77a
Author-email: daniel.westwood@stfc.ac.uk
Requires-Python: >=3.9,<4.0
Classifier: Programming Language :: Python :: 3
Classifier: Programming Language :: Python :: 3.9
Classifier: Programming Language :: Python :: 3.10
Classifier: Programming Language :: Python :: 3.11
Classifier: Programming Language :: Python :: 3.12
Classifier: Programming Language :: Python :: 3.13
